take_note_cli/__init__.py
take_note_cli/__main__.py
take_note_cli/config/config-home-notes.yaml
take_note_cli/config/config-work-notes.yaml
take_note_cli/config/config.yaml
take_note_cli/core/__init__.py
take_note_cli/core/generic_editor_handler.py
take_note_cli/core/notes.py
take_note_cli/core/obsidian_handler.py
take_note_cli/core/vscode_handler.py
take_note_cli/utils/__init__.py
take_note_cli/utils/args.py
take_note_cli/utils/config.py
take_note_cli/utils/dates.py
take_note_cli/utils/paths.py
take_note_cli-2.1.6.dist-info/METADATA
take_note_cli-2.1.6.dist-info/WHEEL
take_note_cli-2.1.6.dist-info/entry_points.txt
take_note_cli-2.1.6.dist-info/licenses/LICENSE
take_note_cli-2.1.6.dist-info/RECORD
