Metadata-Version: 2.4
Name: take-note-cli
Version: 2.1.6
Summary: Create and open notes in your favourite editor.
License: MIT
License-File: LICENSE
Keywords: note,tool,utility,cli
Author: wsinned
Author-email: wsinned@tutanota.com
Requires-Python: >=3.8,<4.0
Classifier: Development Status :: 5 - Production/Stable
Classifier: Environment :: Console
Classifier: Intended Audience :: Developers
Classifier: License :: OSI Approved :: MIT License
Classifier: Natural Language :: English
Classifier: Operating System :: OS Independent
Classifier: Programming Language :: Python :: 3
Classifier: Programming Language :: Python :: 3.8
Classifier: Programming Language :: Python :: 3.9
Classifier: Programming Language :: Python :: 3.10
Classifier: Programming Language :: Python :: 3.11
Classifier: Programming Language :: Python :: 3.12
Classifier: Programming Language :: Python :: 3.13
Classifier: Programming Language :: Python :: 3.14
Classifier: Topic :: Utilities
Requires-Dist: confuse (>=2.0,<3.0)
Project-URL: Homepage, https://github.com/wsinned/take-note
Project-URL: Repository, https://github.com/wsinned/take-note
